pyapollo/__init__.py
pyapollo/apollo_client.py
pyapollo/exceptions.py
scripts/__init__.py
tests/__init__.py
tests/main.py
ke_apollo_client-2.1.2.3.dist-info/LICENSE
ke_apollo_client-2.1.2.3.dist-info/METADATA
ke_apollo_client-2.1.2.3.dist-info/WHEEL
ke_apollo_client-2.1.2.3.dist-info/top_level.txt
ke_apollo_client-2.1.2.3.dist-info/RECORD
