Metadata-Version: 2.1
Name: ke-apollo-client
Version: 2.1.2.3
Summary: a client for apollo 2.0, it's been reformatted!
Home-page: 
Author: zhangxiaojia
Author-email: zhangxiaojia002@ke.com
Platform: any
Classifier: Programming Language :: Python :: 3.5
License-File: LICENSE
Requires-Dist: requests
